read_genbank.py
read_genbank-0.6.data/scripts/read_genbank.py
read_genbank-0.6.dist-info/LICENSE
read_genbank-0.6.dist-info/METADATA
read_genbank-0.6.dist-info/WHEEL
read_genbank-0.6.dist-info/top_level.txt
read_genbank-0.6.dist-info/RECORD
