Metadata-Version: 2.1
Name: read-genbank
Version: 0.6
Summary: A script for parsing GenBank files
Home-page: https://github.com/deprekate/read_genbank
Author: Katelyn McNair
Author-email: deprekate@gmail.com
License: UNKNOWN
Platform: UNKNOWN
Classifier: Programming Language :: Python :: 3
Classifier: License :: OSI Approved :: GNU General Public License v3 or later (GPLv3+)
Classifier: Operating System :: OS Independent
Requires-Python: >3.5.2
License-File: LICENSE
Requires-Dist: rapidfuzz
